rats/__init__.py
rats/app.py
rats/assets/__init__.py
rats/assets/custom.css
rats/assets/download.svg
rats/assets/draggables.js
rats/assets/favicon.ico
rats/assets/graph-up.svg
rats/cache/__init__.py
rats/core/RATS_CONFIG.py
rats/core/__init__.py
rats/core/corecallbacks.py
rats/core/errors.py
rats/core/rats_constructor.py
rats/core/rats_data_tracker.py
rats/core/rats_parser.py
rats/core/session_data_tracker.py
rats/core/topoparser.py
rats/dataframes/__init__.py
rats/modules/__init__.py
rats/modules/data_management/__init__.py
rats/modules/data_management/data_management_callbacks.py
rats/modules/data_management/data_management_view.py
rats/modules/error_detection/__init__.py
rats/modules/error_detection/error_detection_callbacks.py
rats/modules/error_detection/error_detection_plot.py
rats/modules/error_detection/error_detection_view.py
rats/modules/jitter_analysis/__init__.py
rats/modules/jitter_analysis/jitter_analysis_callbacks.py
rats/modules/jitter_analysis/jitter_analysis_view.py
rats/modules/jitter_analysis/jitter_plots.py
rats/modules/scope/__init__.py
rats/modules/scope/scope_callbacks.py
rats/modules/scope/scope_plots.py
rats/modules/scope/scope_view.py
rats/topo/__init__.py
ratpy-1.2.2.dist-info/METADATA
ratpy-1.2.2.dist-info/WHEEL
ratpy-1.2.2.dist-info/top_level.txt
ratpy-1.2.2.dist-info/RECORD
