Metadata-Version: 2.1
Name: ratpy
Version: 1.2.2
Summary: An interpreter and visualiser of RATS files
Author: Steve Ayrton
Author-email: Steve Ayrton <stephen_ayrton@waters.com>
License: BSD
Classifier: Development Status :: 3 - Alpha
Classifier: Intended Audience :: Other Audience
Classifier: Topic :: Scientific/Engineering
Classifier: Programming Language :: Python :: 3.7
Requires-Python: >=3.7
Requires-Dist: pandas (>=1.3.3)
Requires-Dist: dash (>=2.0.0)
Requires-Dist: plotly (>=5.4.0)
Requires-Dist: numpy (>=1.19.5)
Requires-Dist: dash-bootstrap-components (>=1.0.3)
Requires-Dist: beautifulsoup4 (>=4.9.3)
Requires-Dist: pyarrow (>=3.0.0)
Requires-Dist: dash-uploader (>=0.6.0)
Requires-Dist: dash-extensions (>=0.0.70)
Requires-Dist: lxml (>=4.6.2)
